tech_docs_template/__init__.py
tech_docs_template/main.html
tech_docs_template/mkdocs_theme.yml
tech_docs_template/assets/images/govuk-crest-2x.png
tech_docs_template/assets/images/ogl.png
tech_docs_template/assets/stylesheets/extra.css
tech_docs_template/favicons/dbt.ico
tech_docs_template/favicons/moj.ico
tech_docs_template/logos/dbt.png
tech_docs_template/logos/moj.png
mkdocs_tech_docs_template-0.1.2.dist-info/METADATA
mkdocs_tech_docs_template-0.1.2.dist-info/WHEEL
mkdocs_tech_docs_template-0.1.2.dist-info/entry_points.txt
mkdocs_tech_docs_template-0.1.2.dist-info/top_level.txt
mkdocs_tech_docs_template-0.1.2.dist-info/RECORD
