Metadata-Version: 2.1
Name: mkdocs-tech-docs-template
Version: 0.1.2
Summary: MkDocs theme that you can use to build technical documentation with a GOV.UK
Home-page: https://github.com/ministryofjustice/mkdocs-tech-docs-template
Author: Soumaya Mauthoor
Author-email: soumaya.mauthoor@justice.gov.uk
License: MIT
Keywords: mkdocs,technical,documentation
Classifier: Programming Language :: Python :: 3
Classifier: License :: OSI Approved :: MIT License
Classifier: Operating System :: OS Independent
Requires-Dist: mkdocs-material >=9.2.0b1
Provides-Extra: docs
Requires-Dist: markdown-include ; extra == 'docs'
Requires-Dist: mkdocs ; extra == 'docs'
